zeronet/__init__.py
zeronet/core/__init__.py
zeronet/core/function.py
zeronet/core/layer.py
zeronet/core/model.py
zeronet/core/net.py
zeronet/core/optimizer.py
zeronet/utils/__init__.py
zeronet/utils/data_utils.py
zeronet-0.1.3.dist-info/WHEEL
zeronet-0.1.3.dist-info/METADATA
zeronet-0.1.3.dist-info/RECORD
